CHANGELOG.md
README.md
pydantic_socket/__init__.py
pydantic_socket/types.py
pydantic_socket/websocket/__init__.py
pydantic_socket/websocket/base_client.py
pydantic_socket/websocket/client/__init__.py
pydantic_socket/websocket/client/client.py
pydantic_socket/websocket/constants.py
pydantic_socket/websocket/server/__init__.py
pydantic_socket/websocket/server/server.py
pydantic_socket/websocket/server/server_client.py
pydantic_socket-0.1.1.dist-info/LICENSE
pydantic_socket-0.1.1.dist-info/METADATA
pydantic_socket-0.1.1.dist-info/WHEEL
pydantic_socket-0.1.1.dist-info/RECORD
