Metadata-Version: 2.1
Name: pydantic-socket
Version: 0.1.1
Summary: Simple TCP socket client and server with Pydantic models
Home-page: https://github.com/pylakey/pydantic_socket
License: MIT
Author: pylakey
Author-email: pylakey@protonmail.com
Requires-Python: >=3.9,<4.0
Classifier: Framework :: AsyncIO
Classifier: License :: OSI Approved :: MIT License
Classifier: Operating System :: OS Independent
Classifier: Programming Language :: Python :: 3
Classifier: Programming Language :: Python :: 3.9
Classifier: Programming Language :: Python :: 3.10
Classifier: Programming Language :: Python :: 3.11
Classifier: Topic :: Software Development :: Libraries :: Python Modules
Classifier: Typing :: Typed
Requires-Dist: aiohttp[speedups] (>=3.8.4,<4.0.0)
Requires-Dist: pydantic (>=1.10.7,<2.0.0)
Requires-Dist: ujson (>=5.7.0,<6.0.0)
Project-URL: Repository, https://github.com/pylakey/pydantic_socket
